payment_page_sdk/__init__.py
payment_page_sdk/callback.py
payment_page_sdk/gate.py
payment_page_sdk/payment.py
payment_page_sdk/payment_page.py
payment_page_sdk/process_exception.py
payment_page_sdk/signature_handler.py
ecpru_sdk-1.0.4.dist-info/LICENSE
ecpru_sdk-1.0.4.dist-info/METADATA
ecpru_sdk-1.0.4.dist-info/WHEEL
ecpru_sdk-1.0.4.dist-info/top_level.txt
ecpru_sdk-1.0.4.dist-info/RECORD
